gml/__init__.py
gml/compile.py
gimlet_ai-0.0.1.dist-info/METADATA
gimlet_ai-0.0.1.dist-info/WHEEL
gimlet_ai-0.0.1.dist-info/top_level.txt
gimlet_ai-0.0.1.dist-info/RECORD
