Metadata-Version: 2.1
Name: gimlet-ai
Version: 0.0.1
Requires-Dist: torch-mlir-gml
Requires-Dist: torch
